libprot/__init__.py
libprot/amber.py
libprot/cli.py
libprot/misc.py
libprot/pdb.py
libprot/redirect_std_streams.py
libprot/selection.py
libprot-0.1.5.dist-info/AUTHORS.rst
libprot-0.1.5.dist-info/LICENSE
libprot-0.1.5.dist-info/METADATA
libprot-0.1.5.dist-info/WHEEL
libprot-0.1.5.dist-info/entry_points.txt
libprot-0.1.5.dist-info/top_level.txt
libprot-0.1.5.dist-info/RECORD
