Metadata-Version: 2.1
Name: libprot
Version: 0.1.5
Summary: A library of utilities for working with proteins
Home-page: https://bitbucket.org/gusennan/libprot
Author: Nate Guerin
Author-email: nate@textpla.in
License: GNU General Public License v3
Keywords: libprot
Platform: UNKNOWN
Classifier: Development Status :: 2 - Pre-Alpha
Classifier: Intended Audience :: Developers
Classifier: License :: OSI Approved :: GNU General Public License v3 (GPLv3)
Classifier: Natural Language :: English
Classifier: Programming Language :: Python :: 2
Classifier: Programming Language :: Python :: 2.7
Classifier: Programming Language :: Python :: 3
Classifier: Programming Language :: Python :: 3.4
Classifier: Programming Language :: Python :: 3.5
Classifier: Programming Language :: Python :: 3.6
Requires-Dist: Click (>=6.0)
Requires-Dist: numpy (>=1.16.4)
Requires-Dist: biopython (>=1.73)
Requires-Dist: ProDy (>=1.10.10)
Requires-Dist: pyparsing (>=2.4.0)
Requires-Dist: scipy (>=1.3.0)
